satkit-0.9.1.dist-info/RECORD
satkit-0.9.1.dist-info/LICENSE
satkit-0.9.1.dist-info/WHEEL
satkit-0.9.1.dist-info/top_level.txt
satkit-0.9.1.dist-info/METADATA
satkit/planets.pyi
satkit/satkit.pyi
satkit/__init__.pyi
satkit/_version.py
satkit/moon.pyi
satkit/satkit.cpython-38-darwin.so
satkit/__init__.py
satkit/sun.pyi
satkit/frametransform.pyi
satkit/utils.pyi
satkit/density.pyi
satkit/py.typed
satkit/jplephem.pyi
