Metadata-Version: 2.1
Name: satkit
Version: 0.9.1
Summary: Satellite Orbital Dynamics Toolkit
Author-email: Steven Michael <ssmichael@gmail.com>
Maintainer-email: Steven Michael <ssmichael@gmail.com>
License: MIT License
Keywords: satellite,orbit,astrodynamics,SGP4,TLE,JPL,Ephemeris
Classifier: Development Status :: 4 - Beta
Classifier: Programming Language :: Python :: 3.8
Classifier: Programming Language :: Python :: 3.9
Classifier: Programming Language :: Python :: 3.10
Classifier: Programming Language :: Python :: 3.11
Classifier: Programming Language :: Python :: 3.12
Classifier: Programming Language :: Python :: 3.13
Classifier: Programming Language :: Python :: 3.14
Requires-Python: >=3.8
License-File: LICENSE
Requires-Dist: numpy >=1.0.0
Requires-Dist: satkit-data >=0.7.0
Provides-Extra: test
Requires-Dist: pytest ; extra == 'test'
Requires-Dist: xmltodict ; extra == 'test'
